broken_links/__init__.py
broken_links/broken_links.py
broken_links/cli.py
tests/__init__.py
tests/test_check_links.py
tests/test_load_ignore_patterns.py
tests/test_should_ignore.py
broken_links-0.2.0.dist-info/LICENSE
broken_links-0.2.0.dist-info/METADATA
broken_links-0.2.0.dist-info/WHEEL
broken_links-0.2.0.dist-info/entry_points.txt
broken_links-0.2.0.dist-info/top_level.txt
broken_links-0.2.0.dist-info/RECORD
