Metadata-Version: 2.1
Name: broken-links
Version: 0.2.0
Summary: A tool to scrape a website and check for the broken links.
Home-page: https://github.com/merlos/broken-links
Author: merlos
Author-email: merlos@users.noreply.github.com
Classifier: Programming Language :: Python :: 3
Classifier: License :: OSI Approved :: GNU General Public License v3 (GPLv3)
Classifier: Operating System :: OS Independent
Requires-Python: >=3.6
License-File: LICENSE
Requires-Dist: requests
Requires-Dist: beautifulsoup4
